proteomicRuler/__init__.py
proteomicRuler/cli.py
proteomicRuler/constant.py
proteomicRuler/histones.py
proteomicRuler/organisms.json
proteomicRuler/ruler.py
proteomicRuler/test_cli.py
proteomicRuler/test_ruler.py
proteomicruler-0.1.6.dist-info/entry_points.txt
proteomicruler-0.1.6.dist-info/LICENSE
proteomicruler-0.1.6.dist-info/METADATA
proteomicruler-0.1.6.dist-info/WHEEL
proteomicruler-0.1.6.dist-info/RECORD
