Metadata-Version: 2.1
Name: proteomicruler
Version: 0.1.6
Summary: Estimate copy number from deep profile MS experiment using the Proteomic Ruler algorithm from Wiśniewski, J. R., Hein, M. Y., Cox, J. and Mann, M. (2014) A “Proteomic Ruler” for Protein Copy Number and Concentration Estimation without Spike-in Standards. Mol Cell Proteomics 13, 3497–3506.
Home-page: https://github.com/noatgnu/proteomicRuler
License: MIT
Keywords: proteomic,ruler,histone,mass spectrometry
Author: Toan K. Phung
Author-email: toan.phungkhoiquoctoan@gmail.com
Requires-Python: >=3.11,<=3.13
Classifier: License :: OSI Approved :: MIT License
Classifier: Programming Language :: Python :: 3
Classifier: Programming Language :: Python :: 3.11
Classifier: Programming Language :: Python :: 3.12
Requires-Dist: click (>=8.3.0,<9.0.0)
Requires-Dist: pandas (>=2.3.3,<3.0.0)
Requires-Dist: requests (==2.32.4)
Requires-Dist: scipy (>=1.16.2,<2.0.0)
Requires-Dist: seaborn (>=0.13.2,<0.14.0)
Requires-Dist: uniprotparser (>=1.2.1,<2.0.0)
Project-URL: Repository, https://github.com/noatgnu/proteomicRuler
